MANIFEST.in
README.md
VERSION
setup.cfg
setup.py
deps/jars/spark-hyperloglog-assembly-2.1.1-SNAPSHOT.jar
pyspark_hyperloglog.egg-info/PKG-INFO
pyspark_hyperloglog.egg-info/SOURCES.txt
pyspark_hyperloglog.egg-info/dependency_links.txt
pyspark_hyperloglog.egg-info/requires.txt
pyspark_hyperloglog.egg-info/top_level.txt
src/__init__.py
src/hll.py